<?xml version="1.0" encoding="utf-8" ?><dwsync><file name="abbr.htm" server="ftp.amalgamotion.com" local="3368641108" remote="11964982652" /><file name="acronym.htm" server="ftp.amalgamotion.com" local="3368641108" remote="11964982652" /><file name="attributes.htm" server="ftp.amalgamotion.com" local="3368641108" remote="11964982652" /><file name="cite.htm" server="ftp.amalgamotion.com" local="3368641108" remote="11964982652" /><file name="del.htm" server="ftp.amalgamotion.com" local="3368641108" remote="11964982652" /><file name="editor_plugin.js" server="ftp.amalgamotion.com" local="3368641106" remote="11964982652" /><file name="editor_plugin_src.js" server="ftp.amalgamotion.com" local="3368641106" remote="11964982652" /><file name="ins.htm" server="ftp.amalgamotion.com" local="3368641108" remote="11964982652" /></dwsync>